recallbricks_langchain/__init__.py
recallbricks_langchain/agents.py
recallbricks_langchain/chat_history.py
recallbricks_langchain/client.py
recallbricks_langchain/collaboration.py
recallbricks_langchain/learning.py
recallbricks_langchain/memories.py
recallbricks_langchain/memory.py
recallbricks_langchain/monitoring.py
recallbricks_langchain/relationships.py
recallbricks_langchain/retriever.py
recallbricks_langchain/usage.py
recallbricks_langchain-2.0.1.dist-info/licenses/LICENSE
tests/__init__.py
tests/breaking_tests.py
tests/breaking_tests_fast.py
tests/load_test.py
tests/stress_test.py
tests/test_bulletproof_features.py
tests/test_chat_history.py
tests/test_client.py
tests/test_collaboration_api.py
tests/test_learn_recall.py
tests/test_learning_api.py
tests/test_memories_api.py
tests/test_memory.py
tests/test_monitoring_api.py
tests/test_relationships_api.py
tests/test_retriever.py
tests/test_sdk_simulation.py
tests/test_usage_api.py
recallbricks_langchain-2.0.1.dist-info/METADATA
recallbricks_langchain-2.0.1.dist-info/WHEEL
recallbricks_langchain-2.0.1.dist-info/top_level.txt
recallbricks_langchain-2.0.1.dist-info/RECORD
