Metadata-Version: 2.4
Name: recallbricks-langchain
Version: 2.0.1
Summary: Enterprise-grade persistent memory for LangChain agents
Home-page: https://github.com/recallbricks/recallbricks-langchain
Author: RecallBricks
Author-email: tyler.kutscher@gmail.com
Classifier: Programming Language :: Python :: 3
Classifier: License :: OSI Approved :: MIT License
Classifier: Operating System :: OS Independent
Requires-Python: >=3.8
License-File: LICENSE
Requires-Dist: requests>=2.31.0
Requires-Dist: langchain>=0.1.0
Dynamic: author
Dynamic: author-email
Dynamic: classifier
Dynamic: description
Dynamic: description-content-type
Dynamic: home-page
Dynamic: license-file
Dynamic: requires-dist
Dynamic: requires-python
Dynamic: summary
